QukuaiLianJishuZhinan090/README.md
QukuaiLianJishuZhinan090/__init__.py
QukuaiLianJishuZhinan090/__main__.py
QukuaiLianJishuZhinan090/file.epub
QukuaiLianJishuZhinan090/index.html
QukuaiLianJishuZhinan090/css/__init__.py
QukuaiLianJishuZhinan090/css/annotations.css
QukuaiLianJishuZhinan090/css/main.css
QukuaiLianJishuZhinan090/css/normalize.css
QukuaiLianJishuZhinan090/css/popup.css
QukuaiLianJishuZhinan090/font/__init__.py
QukuaiLianJishuZhinan090/font/fontello.eot
QukuaiLianJishuZhinan090/font/fontello.svg
QukuaiLianJishuZhinan090/font/fontello.ttf
QukuaiLianJishuZhinan090/font/fontello.woff
QukuaiLianJishuZhinan090/img/__init__.py
QukuaiLianJishuZhinan090/img/annotator-glyph-sprite.png
QukuaiLianJishuZhinan090/img/annotator-icon-sprite.png
QukuaiLianJishuZhinan090/img/apple-touch-icon.png
QukuaiLianJishuZhinan090/img/cancelfullscreen.png
QukuaiLianJishuZhinan090/img/close.png
QukuaiLianJishuZhinan090/img/fullscreen.png
QukuaiLianJishuZhinan090/img/loader.gif
QukuaiLianJishuZhinan090/img/menu-icon.png
QukuaiLianJishuZhinan090/img/save.png
QukuaiLianJishuZhinan090/img/saved.png
QukuaiLianJishuZhinan090/img/settings-s.png
QukuaiLianJishuZhinan090/img/settings.png
QukuaiLianJishuZhinan090/img/star.png
QukuaiLianJishuZhinan090/js/__init__.py
QukuaiLianJishuZhinan090/js/epub.js
QukuaiLianJishuZhinan090/js/epub.min.js
QukuaiLianJishuZhinan090/js/epub.min.map
QukuaiLianJishuZhinan090/js/hooks.min.js
QukuaiLianJishuZhinan090/js/hooks.min.map
QukuaiLianJishuZhinan090/js/reader.js
QukuaiLianJishuZhinan090/js/reader.js.map
QukuaiLianJishuZhinan090/js/reader.min.js
QukuaiLianJishuZhinan090/js/reader.min.map
QukuaiLianJishuZhinan090/js/hooks/__init__.py
QukuaiLianJishuZhinan090/js/hooks/extensions/__init__.py
QukuaiLianJishuZhinan090/js/hooks/extensions/highlight.js
QukuaiLianJishuZhinan090/js/libs/__init__.py
QukuaiLianJishuZhinan090/js/libs/jquery.min.js
QukuaiLianJishuZhinan090/js/libs/localforage.min.js
QukuaiLianJishuZhinan090/js/libs/screenfull.js
qukuai_lian_jishu_zhinan_0_9_0-2024.3.2.0.dist-info/METADATA
qukuai_lian_jishu_zhinan_0_9_0-2024.3.2.0.dist-info/WHEEL
qukuai_lian_jishu_zhinan_0_9_0-2024.3.2.0.dist-info/entry_points.txt
qukuai_lian_jishu_zhinan_0_9_0-2024.3.2.0.dist-info/top_level.txt
qukuai_lian_jishu_zhinan_0_9_0-2024.3.2.0.dist-info/RECORD
